{
    "model": "TextSection",
    "srcType": "git",
    "srcProjectId": "9a0364b9",
    "presets": [
        {
            "label": "Event Layout",
            "locale": null,
            "metadata": {
                "categories": [
                    "Event"
                ],
                "canDelete": true
            },
            "data": {
                "colors": "colors-f",
                "variant": "variant-a",
                "title": "Event: Rethinking Capitalism",
                "subtitle": "Economics where People and the Environment matter",
                "text": "This two-day seminar includes discussion on some of the most pressing economic issues facing the world today.\n\nTopics include inequality, insecurity, climate change, the national budget and a campaign for a fairer and more sustainable economy, drawn from modern monetary theory and ecological economics.\n\n**Course outline:** Adapted from a university economics subject, the course is divided into ten units, most of which feature a 20-30 minute introduction, a 10-15 minute video and at least 20 minutes of small-group discussion. The timetable is subject to minor changes, but this will give some idea of the scope of the course.\n\n**Facilitator:** Associate Professor [Steven Hail](https://www.linkedin.com/in/steven-hail-27b7b910), Lecturer at Torrens University Australia and Economist at Modern Money Lab.\n\n###### *DAY ONE*\n\n10:00-10:10 Welcome, housekeeping\n\n10:10-11:30 Part One: Rethinking Value\n\n11.30-12:00 Morning Tea\n\n12:00-1:00 Part Two: Ecological Economics and the Doughnut\n\n1:00-2:00 Lunch\n\n2:00-3:00 Part Three: The Deficit Myth\n\n3:00-3.30 Afternoon Tea\n\n3:30-4.30 Part Four: Income Inequality and Well-Being\n\nEvening Social\n\n###### *DAY TWO*\n\n10:00-11.00 Part Five: An Economics Fit for Humans\n\n11:00-11:30 Morning Tea\n\n11.30-12:30 Part Six: Rethinking Trade and Development\n\n12:30-1:30 Lunch\n\n1:30-2:30 Part Seven: A National Job Guarantee\n\n2:30-3:00 Afternoon Tea\n\n3:00-4:00 Part Eight: Freeing the State from Capture\n\n4.00-4:30 Part Nine: Conclusion - Planting a Tree\n\nTickets are available [here](https://example.com)\n",
                "elementId": "",
                "styles": {
                    "self": {
                        "height": "auto",
                        "width": "narrow",
                        "padding": [
                            "pt-12",
                            "pb-36",
                            "pl-4",
                            "pr-4"
                        ],
                        "justifyContent": "center"
                    },
                    "title": {
                        "textAlign": "left"
                    },
                    "subtitle": {
                        "textAlign": "left"
                    },
                    "text": {
                        "textAlign": "left"
                    }
                }
            },
            "thumbnail": "images/text-section-event-layout-fbeb.png"
        }
    ]
}
